{
    "KeyTable": [
        {
            "Origin": 2, 
            "Comment": "power toggle", 
            "KeyEvent": 0, 
            "TimeOutList": [], 
            "Action": 1, 
            "KeyList": [
                76
            ]
        }, 
        {
            "Origin": 6, 
            "Comment": "power toggle", 
            "KeyEvent": 0, 
            "TimeOutList": [], 
            "Action": 1, 
            "KeyList": [
                76
            ]
        }, 
        {
            "Origin": 2, 
            "Comment": "source select", 
            "KeyEvent": 0, 
            "TimeOutList": [], 
            "Action": 2, 
            "KeyList": [
                129
            ]
        }, 
        {
            "Origin": 6, 
            "Comment": "source select", 
            "KeyEvent": 0, 
            "TimeOutList": [], 
            "Action": 2, 
            "KeyList": [
                129
            ]
        }, 
        {
            "Origin": 2, 
            "Comment": "preset 1", 
            "KeyEvent": 0, 
            "TimeOutList": [], 
            "Action": 3, 
            "KeyList": [
                65
            ]
        }, 
        {
            "Origin": 6, 
            "Comment": "preset 1", 
            "KeyEvent": 0, 
            "TimeOutList": [], 
            "Action": 3, 
            "KeyList": [
                65
            ]
        }, 
        {
            "Origin": 2, 
            "Comment": "preset 2", 
            "KeyEvent": 0, 
            "TimeOutList": [], 
            "Action": 4, 
            "KeyList": [
                66
            ]
        }, 
        {
            "Origin": 6, 
            "Comment": "preset 2", 
            "KeyEvent": 0, 
            "TimeOutList": [], 
            "Action": 4, 
            "KeyList": [
                66
            ]
        }, 
        {
            "Origin": 2, 
            "Comment": "preset 3", 
            "KeyEvent": 0, 
            "TimeOutList": [], 
            "Action": 5, 
            "KeyList": [
                67
            ]
        }, 
        {
            "Origin": 6, 
            "Comment": "preset 3", 
            "KeyEvent": 0, 
            "TimeOutList": [], 
            "Action": 5, 
            "KeyList": [
                67
            ]
        }, 
        {
            "Origin": 2, 
            "Comment": "preset 4", 
            "KeyEvent": 0, 
            "TimeOutList": [], 
            "Action": 6, 
            "KeyList": [
                68
            ]
        }, 
        {
            "Origin": 6, 
            "Comment": "preset 4", 
            "KeyEvent": 0, 
            "TimeOutList": [], 
            "Action": 6, 
            "KeyList": [
                68
            ]
        }, 
        {
            "Origin": 2, 
            "Comment": "preset 5", 
            "KeyEvent": 0, 
            "TimeOutList": [], 
            "Action": 7, 
            "KeyList": [
                69
            ]
        }, 
        {
            "Origin": 6, 
            "Comment": "preset 5", 
            "KeyEvent": 0, 
            "TimeOutList": [], 
            "Action": 7, 
            "KeyList": [
                69
            ]
        }, 
        {
            "Origin": 2, 
            "Comment": "preset 6", 
            "KeyEvent": 0, 
            "TimeOutList": [], 
            "Action": 8, 
            "KeyList": [
                70
            ]
        }, 
        {
            "Origin": 6, 
            "Comment": "preset 6", 
            "KeyEvent": 0, 
            "TimeOutList": [], 
            "Action": 8, 
            "KeyList": [
                70
            ]
        }, 
        {
            "Origin": 2, 
            "Comment": "volume up", 
            "KeyEvent": 1, 
            "TimeOutList": [
                0
            ], 
            "Action": 23, 
            "KeyList": [
                3
            ]
        }, 
        {
            "Origin": 6, 
            "Comment": "volume up", 
            "KeyEvent": 1, 
            "TimeOutList": [
                0
            ], 
            "Action": 23, 
            "KeyList": [
                3
            ]
        }, 
        {
            "Origin": 4, 
            "Comment": "volume up", 
            "KeyEvent": 1, 
            "TimeOutList": [
                0
            ], 
            "Action": 23, 
            "KeyList": [
                3
            ]
        }, 
        {
            "Origin": 2, 
            "Comment": "volume up repeat", 
            "KeyEvent": 3, 
            "TimeOutList": [
                300, 
                100
            ], 
            "Action": 23, 
            "KeyList": [
                3
            ]
        }, 
        {
            "Origin": 6, 
            "Comment": "volume up repeat", 
            "KeyEvent": 3, 
            "TimeOutList": [
                300, 
                100
            ], 
            "Action": 23, 
            "KeyList": [
                3
            ]
        }, 
        {
            "Origin": 4, 
            "Comment": "volume up repeat", 
            "KeyEvent": 3, 
            "TimeOutList": [
                300, 
                100
            ], 
            "Action": 23, 
            "KeyList": [
                3
            ]
        }, 
        {
            "Origin": 2, 
            "Comment": "volume down", 
            "KeyEvent": 1, 
            "TimeOutList": [
                0
            ], 
            "Action": 25, 
            "KeyList": [
                2
            ]
        }, 
        {
            "Origin": 6, 
            "Comment": "volume down", 
            "KeyEvent": 1, 
            "TimeOutList": [
                0
            ], 
            "Action": 25, 
            "KeyList": [
                2
            ]
        }, 
        {
            "Origin": 4, 
            "Comment": "volume down", 
            "KeyEvent": 1, 
            "TimeOutList": [
                0
            ], 
            "Action": 25, 
            "KeyList": [
                2
            ]
        }, 
        {
            "Origin": 2, 
            "Comment": "volume down repeat", 
            "KeyEvent": 3, 
            "TimeOutList": [
                300, 
                100
            ], 
            "Action": 25, 
            "KeyList": [
                2
            ]
        }, 
        {
            "Origin": 6, 
            "Comment": "volume down repeat", 
            "KeyEvent": 3, 
            "TimeOutList": [
                300, 
                100
            ], 
            "Action": 25, 
            "KeyList": [
                2
            ]
        }, 
        {
            "Origin": 4, 
            "Comment": "volume down repeat", 
            "KeyEvent": 3, 
            "TimeOutList": [
                300, 
                100
            ], 
            "Action": 25, 
            "KeyList": [
                2
            ]
        }, 
        {
            "Origin": 2, 
            "Comment": "play/pause", 
            "KeyEvent": 0, 
            "TimeOutList": [], 
            "Action": 9, 
            "KeyList": [
                85
            ]
        }, 
        {
            "Origin": 6, 
            "Comment": "play/pause", 
            "KeyEvent": 0, 
            "TimeOutList": [], 
            "Action": 9, 
            "KeyList": [
                85
            ]
        }, 
        {
            "Origin": 2, 
            "Comment": "skip forward", 
            "KeyEvent": 0, 
            "TimeOutList": [], 
            "Action": 10, 
            "KeyList": [
                90
            ]
        }, 
        {
            "Origin": 6, 
            "Comment": "skip forward", 
            "KeyEvent": 0, 
            "TimeOutList": [], 
            "Action": 10, 
            "KeyList": [
                90
            ]
        }, 
        {
            "Origin": 2, 
            "Comment": "skip back", 
            "KeyEvent": 0, 
            "TimeOutList": [], 
            "Action": 11, 
            "KeyList": [
                89
            ]
        }, 
        {
            "Origin": 6, 
            "Comment": "skip back", 
            "KeyEvent": 0, 
            "TimeOutList": [], 
            "Action": 11, 
            "KeyList": [
                89
            ]
        }, 
        {
            "Origin": 2, 
            "Comment": "mute toggle", 
            "KeyEvent": 0, 
            "TimeOutList": [], 
            "Action": 12, 
            "KeyList": [
                1
            ]
        }, 
        {
            "Origin": 6, 
            "Comment": "mute toggle", 
            "KeyEvent": 0, 
            "TimeOutList": [], 
            "Action": 12, 
            "KeyList": [
                1
            ]
        }, 
        {
            "Origin": 2, 
            "Comment": "select soundtouch", 
            "KeyEvent": 0, 
            "TimeOutList": [], 
            "Action": 13, 
            "KeyList": [
                179
            ]
        }, 
        {
            "Origin": 6, 
            "Comment": "select soundtouch", 
            "KeyEvent": 0, 
            "TimeOutList": [], 
            "Action": 13, 
            "KeyList": [
                179
            ]
        }, 
        {
            "Origin": 2, 
            "Comment": "connect", 
            "KeyEvent": 0, 
            "TimeOutList": [], 
            "Action": 14, 
            "KeyList": [
                17
            ]
        }, 
        {
            "Origin": 6, 
            "Comment": "connect", 
            "KeyEvent": 0, 
            "TimeOutList": [], 
            "Action": 14, 
            "KeyList": [
                17
            ]
        }, 
        {
            "Origin": 2, 
            "Comment": "vpa", 
            "KeyEvent": 0, 
            "TimeOutList": [], 
            "Action": 15, 
            "KeyList": [
                18
            ]
        }, 
        {
            "Origin": 6, 
            "Comment": "vpa", 
            "KeyEvent": 0, 
            "TimeOutList": [], 
            "Action": 15, 
            "KeyList": [
                18
            ]
        }, 
        {
            "Origin": 2, 
            "Comment": "select tv", 
            "KeyEvent": 0, 
            "TimeOutList": [], 
            "Action": 16, 
            "KeyList": [
                14
            ]
        }, 
        {
            "Origin": 6, 
            "Comment": "select tv", 
            "KeyEvent": 0, 
            "TimeOutList": [], 
            "Action": 16, 
            "KeyList": [
                14
            ]
        }, 
        {
            "Origin": 2, 
            "Comment": "thumbs up", 
            "KeyEvent": 0, 
            "TimeOutList": [], 
            "Action": 17, 
            "KeyList": [
                107
            ]
        }, 
        {
            "Origin": 6, 
            "Comment": "thumbs up", 
            "KeyEvent": 0, 
            "TimeOutList": [], 
            "Action": 17, 
            "KeyList": [
                107
            ]
        }, 
        {
            "Origin": 2, 
            "Comment": "thumbs down", 
            "KeyEvent": 0, 
            "TimeOutList": [], 
            "Action": 18, 
            "KeyList": [
                106
            ]
        }, 
        {
            "Origin": 6, 
            "Comment": "thumbs down", 
            "KeyEvent": 0, 
            "TimeOutList": [], 
            "Action": 18, 
            "KeyList": [
                106
            ]
        }, 
        {
            "Origin": 2, 
            "Comment": "factory default", 
            "KeyEvent": 2, 
            "TimeOutList": [
                5000
            ], 
            "Action": 19, 
            "KeyList": [
                253
            ]
        }, 
        {
            "Origin": 6, 
            "Comment": "factory default", 
            "KeyEvent": 2, 
            "TimeOutList": [
                5000
            ], 
            "Action": 19, 
            "KeyList": [
                253
            ]
        }, 
        {
            "Origin": 2, 
            "Comment": "wifi off", 
            "KeyEvent": 2, 
            "TimeOutList": [
                3000
            ], 
            "Action": 20, 
            "KeyList": [
                252
            ]
        }, 
        {
            "Origin": 6, 
            "Comment": "wifi off", 
            "KeyEvent": 2, 
            "TimeOutList": [
                3000
            ], 
            "Action": 20, 
            "KeyList": [
                252
            ]
        }, 
        {
            "Origin": 2, 
            "Comment": "ap setup", 
            "KeyEvent": 2, 
            "TimeOutList": [
                3000
            ], 
            "Action": 21, 
            "KeyList": [
                251
            ]
        }, 
        {
            "Origin": 6, 
            "Comment": "ap setup", 
            "KeyEvent": 2, 
            "TimeOutList": [
                3000
            ], 
            "Action": 21, 
            "KeyList": [
                251
            ]
        }, 
        {
            "Origin": 2, 
            "Comment": "pair speakers", 
            "KeyEvent": 2, 
            "TimeOutList": [
                3000
            ], 
            "Action": 22, 
            "KeyList": [
                250
            ]
        }, 
        {
            "Origin": 6, 
            "Comment": "pair speakers", 
            "KeyEvent": 2, 
            "TimeOutList": [
                3000
            ], 
            "Action": 22, 
            "KeyList": [
                250
            ]
        }, 
        {
            "Origin": 1, 
            "Comment": "mute toggle", 
            "KeyEvent": 0, 
            "TimeOutList": [], 
            "Action": 12, 
            "KeyList": [
                1
            ]
        }, 
        {
            "Origin": 1, 
            "Comment": "vpa", 
            "KeyEvent": 0, 
            "TimeOutList": [], 
            "Action": 15, 
            "KeyList": [
                18
            ]
        }
    ]
}