<?xml version="1.0" encoding="UTF-8" ?>
<sources>
    <source displayName="TV" visible="true" local="true" multiroom="true" status="NOT_CONFIGURED">
        <sourceKey type="PRODUCT" account="TV" accountid="TV" />
    </source>
    <source displayName="SLOT_0" visible="false" local="true" multiroom="true" status="NOT_CONFIGURED">
        <sourceKey type="PRODUCT" account="SLOT_0" accountid="SLOT_0" />
    </source>
    <source displayName="SLOT_1" visible="false" local="true" multiroom="true" status="NOT_CONFIGURED">
        <sourceKey type="PRODUCT" account="SLOT_1" accountid="SLOT_1" />
    </source>
    <source displayName="SLOT_2" visible="false" local="true" multiroom="true" status="NOT_CONFIGURED">
        <sourceKey type="PRODUCT" account="SLOT_2" accountid="SLOT_2" />
    </source>
    <source displayName="SETUP" visible="false" local="true" multiroom="false" status="UNAVAILABLE">
        <sourceKey type="SETUP" account="SETUP" accountid="SETUP" />
    </source>
    <source displayName="ADAPTIQ" visible="false" local="true" multiroom="false" status="UNAVAILABLE">
        <sourceKey type="SETUP" account="ADAPTIQ" accountid="ADAPTIQ" />
    </source>
    <source displayName="PAIRING" visible="false" local="true" multiroom="false" status="UNAVAILABLE">
        <sourceKey type="SETUP" account="PAIRING" accountid="PAIRING" />
    </source>
    <properties activationKeyRequired="true" deviceTypeRequired="true" friendlyNameRequired="false" inputRouteRequired="false" supportedInputRoutes="INPUT_ROUTE_TV" supportedActivationKeys="ACTIVATION_KEY_NONE;ACTIVATION_KEY_GAME;ACTIVATION_KEY_CBL_SAT;ACTIVATION_KEY_BD_DVD;ACTIVATION_KEY_TV" supportedFriendlyNames="FRIENDLY_NAME_CABLE_BOX;FRIENDLY_NAME_SAT_BOX;FRIENDLY_NAME_HDTV_TUNER;FRIENDLY_NAME_DIGITIAL_TV_TUNER;FRIENDLY_NAME_VCR;FRIENDLY_NAME_DVR;FRIENDLY_NAME_TIVO;FRIENDLY_NAME_SET_TOP_BOX;FRIENDLY_NAME_APPLE_TV;FRIENDLY_NAME_VUDU;FRIENDLY_NAME_DVD_PLAYER;FRIENDLY_NAME_BLURAY_PLAYER;FRIENDLY_NAME_DVD_RECORDER;FRIENDLY_NAME_BLURAY_RECORDER;FRIENDLY_NAME_CD_PLAYER;FRIENDLY_NAME_DIGITIAL_MEDIA_PLAYER;FRIENDLY_NAME_PLAYSTATION;FRIENDLY_NAME_XBOX;FRIENDLY_NAME_WII;FRIENDLY_NAME_GAME_CONSOLE;FRIENDLY_NAME_ROKU;FRIENDLY_NAME_COMPUTER;FRIENDLY_NAME_IPOD;FRIENDLY_NAME_RADIO_TUNER;FRIENDLY_NAME_XBOX_ONE;FRIENDLY_NAME_XBOX_360;FRIENDLY_NAME_AMAZON_FIRE_TV;FRIENDLY_NAME_CHROMECAST;FRIENDLY_NAME_TV;FRIENDLY_NAME_BLUETOOTH" supportedDeviceTypes="DEVICE_TYPE_TV;DEVICE_TYPE_SMART_TV;DEVICE_TYPE_GAME;DEVICE_TYPE_CBL_SAT;DEVICE_TYPE_BD_DVD;DEVICE_TYPE_STREAMING" />
</sources>
